{"track": "Snetterton", "event": "British GT4 Snetterton", "duration": ".5", "date": "20211120", "game": "ACC", "series": "ACC Season 3 - British GT4", "fastest_lap": ["Woody"], "drivers": [{"name": "Termin", "pos": "1"}, {"name": "QBDLettuce", "pos": "2"}, {"name": "Tom Cook", "pos": "3"}, {"name": "Woody", "pos": "4"}, {"name": "LordFlipFlap", "pos": "5"}, {"name": "Evan", "pos": "6"}, {"name": "Jack Mekov", "pos": "7"}, {"name": "Crashneck", "pos": "8"}, {"name": "CraigMeUp", "pos": "9"}, {"name": "Callum McCarthy", "pos": "10"}, {"name": "Fried04", "pos": "11"}, {"name": "Jetyh", "pos": "12"}, {"name": "Neusor", "pos": "DNF"}]}